iot/__init__.py
iot/config.py
iot/context.py
iot/factories.py
iot/hooks.py
iot/messages.py
iot/models.py
iot/pipeline.py
iot/semantics.py
iot/terminal.py
iot/utils.py
iot/core/__init__.py
iot/core/acoustics/__init__.py
iot/core/acoustics/asr.py
iot/core/acoustics/tts.py
iot/core/hardware/__init__.py
iot/core/hardware/player.py
iot/core/hardware/recorder.py
iot/core/semantics/__init__.py
iot/core/semantics/button.py
iot/core/semantics/dialog.py
iot/core/semantics/light.py
iot/core/semantics/qq.py
iot/core/semantics/switch.py
iot/integration/__init__.py
iot/integration/audio.py
iot/integration/baidu.py
iot/integration/mqtt.py
fubuki_iot-0.3.dist-info/LICENSE
fubuki_iot-0.3.dist-info/METADATA
fubuki_iot-0.3.dist-info/WHEEL
fubuki_iot-0.3.dist-info/top_level.txt
fubuki_iot-0.3.dist-info/RECORD
