Metadata-Version: 2.1
Name: fubuki-iot
Version: 0.3
Summary: An accessable Iot Terminal implementated by Python
Home-page: https://github.com/littlebutt/fubuki-iot
Author: littlebutt
Author-email: luogan1996@icloud.com
License: MIT License
Requires-Python: >=3.8
License-File: LICENSE
Requires-Dist: keyboard (>=0.13.5)
Requires-Dist: loguru (>=0.6.0)
Requires-Dist: paho-mqtt (>=1.6.1)
Requires-Dist: PyAudio (>=0.2.12)
Requires-Dist: pydantic (>=1.10.2)
Requires-Dist: python-dotenv (>=0.21.0)
Requires-Dist: requests (>=2.28.1)
